cli_todo_kor/__init__.py
cli_todo_kor/core.py
cli_todo_kor/display.py
cli_todo_kor/todo.py
cli_todo_kor/undo.py
cli_todo_kor/utils.py
cli_todo_kor-0.3.2.dist-info/METADATA
cli_todo_kor-0.3.2.dist-info/WHEEL
cli_todo_kor-0.3.2.dist-info/entry_points.txt
cli_todo_kor-0.3.2.dist-info/top_level.txt
cli_todo_kor-0.3.2.dist-info/RECORD
