Metadata-Version: 2.4
Name: cli-todo-kor
Version: 0.3.2
Summary: 한글 CLI Todo List 프로그램
Author-email: sis9772 <sis9772@naver.com>
Requires-Python: >=3.7
Requires-Dist: platformdirs
Requires-Dist: wcwidth
